swa/__init__.py
swa/callback.py
swa/keras.py
swa/tfkeras.py
keras_swa-0.1.6.dist-info/LICENSE
keras_swa-0.1.6.dist-info/METADATA
keras_swa-0.1.6.dist-info/WHEEL
keras_swa-0.1.6.dist-info/top_level.txt
keras_swa-0.1.6.dist-info/RECORD
