Metadata-Version: 2.1
Name: keras-swa
Version: 0.1.6
Summary: Simple stochastic weight averaging callback for Keras.
Home-page: https://github.com/simon-larsson/keras-swa
Author: Simon Larsson
Author-email: larssonsimon0@gmail.com
License: MIT
Platform: UNKNOWN
Classifier: License :: OSI Approved :: MIT License
Classifier: Programming Language :: Python :: 3 :: Only
Classifier: Topic :: Scientific/Engineering
